{"name":"Buildings","guid":1,"components":[{"type":"DG.TableView","guid":43,"componentStorage":{"_links_":{"context":{"type":"DG.DataContextRecord","id":2}},"attributeWidths":[{"_links_":{"attr":{"type":"DG.Attribute","id":4}},"width":60},{"_links_":{"attr":{"type":"DG.Attribute","id":5}},"width":60},{"_links_":{"attr":{"type":"DG.Attribute","id":6}},"width":113},{"_links_":{"attr":{"type":"DG.Attribute","id":7}},"width":60},{"_links_":{"attr":{"type":"DG.Attribute","id":9}},"width":60},{"_links_":{"attr":{"type":"DG.Attribute","id":10}},"width":60},{"_links_":{"attr":{"type":"DG.Attribute","id":11}},"width":84}],"title":"Buildings"},"layout":{"width":688,"height":200,"left":50,"top":5,"zIndex":264,"isVisible":true},"savedHeight":null},{"type":"DG.GraphView","guid":45,"componentStorage":{"_links_":{"context":{"type":"DG.DataContextRecord","id":2},"legendColl":{"type":"DG.Collection","id":48},"legendAttr":{"type":"DG.Attribute","id":8},"hiddenCases":[],"xColl":{"type":"DG.Collection","id":3},"xAttr":{"type":"DG.Attribute","id":5},"yColl":{"type":"DG.Collection","id":3},"yAttr":{"type":"DG.Attribute","id":4}},"legendRole":0,"legendAttributeType":2,"pointColor":"#e6805b","strokeColor":"lightgrey","pointSizeMultiplier":1,"transparency":0.85,"strokeTransparency":0.4,"isTransparent":false,"plotBackgroundColor":null,"plotBackgroundOpacity":1,"xRole":1,"xAttributeType":1,"yRole":4,"yAttributeType":1,"y2Role":0,"y2AttributeType":0,"xAxisClass":"DG.CellLinearAxisModel","xLowerBound":-10,"xUpperBound":130,"yAxisClass":"DG.CellLinearAxisModel","yLowerBound":-100,"yUpperBound":1700,"y2AxisClass":"DG.AxisModel","plotModels":[{"plotModelStorage":{"verticalAxisIsY2":false,"movableLineStorage":{"isVisible":true,"intercept":61.53796512840535,"slope":12.826365327922,"isInterceptLocked":false,"isVertical":false,"xIntercept":null}},"plotClass":"DG.ScatterPlotModel"}],"title":"Number of Building Stories vs. Building Height"},"layout":{"width":450,"height":445,"left":45,"top":210,"zIndex":249,"isVisible":true},"savedHeight":null},{"type":"DG.GuideView","guid":46,"componentStorage":{"items":[{"itemTitle":"Getting Started","url":"https://concord-consortium.github.io/codap-data/FathomDocs/Mathematics/Algebra/Buildings/Buildings.html"}],"currentURL":"https://concord-consortium.github.io/codap-data/FathomDocs/Mathematics/Algebra/Buildings/Buildings.html","currentItemTitle":"Getting Started","isVisible":true},"layout":{"left":755,"top":10,"width":405,"height":545,"zIndex":269,"isVisible":true},"savedHeight":null},{"type":"DG.MapView","guid":64,"componentStorage":{"_links_":{"context":{"type":"DG.DataContextRecord","id":2},"hiddenCases":[]},"legendRole":0,"legendAttributeType":0,"pointColor":"#e6805b","strokeColor":"white","pointSizeMultiplier":1,"transparency":0.85,"strokeTransparency":0.4,"mapModelStorage":{"center":{"lat":35.88905007936091,"lng":-98.0859375},"zoom":2,"baseMapLayerName":"Topographic","pointsShouldBeVisible":true,"linesShouldBeVisible":false,"grid":{"gridMultiplier":1,"visible":false},"areaColor":"#FF3E00","areaTransparency":"0.5","areaStrokeColor":"white","areaStrokeTransparency":"0.6"},"title":"Buildings"},"layout":{"width":240,"height":190,"left":500,"top":210,"zIndex":262,"isVisible":true},"savedHeight":null}],"contexts":[{"type":"DG.DataContext","document":1,"guid":2,"flexibleGroupingChangeFlag":true,"name":"Buildings","collections":[{"areParentChildLinksConfigured":false,"attrs":[{"name":"state","type":null,"title":"state","description":"","colormap":{"MN":{"h":0.23809523809523814,"s":0.6666666666666666,"b":1,"colorString":"rgb(182,255,85)"},"FL":{"h":0.39809523809523817,"s":0.6666666666666666,"b":1,"colorString":"rgb(85,255,151)"},"IL":{"h":0.5580952380952382,"s":0.6666666666666666,"b":1,"colorString":"rgb(85,196,255)"},"CA":{"h":0.7180952380952382,"s":0.6666666666666666,"b":1,"colorString":"rgb(137,85,255)"},"NY":{"h":0.8780952380952382,"s":0.6666666666666666,"b":1,"colorString":"rgb(255,85,209)"}},"blockDisplayOfEmptyCategories":true,"editable":false,"guid":9,"precision":2,"unit":null}],"cases":[{"guid":59,"values":{"state":"MN"}},{"guid":60,"values":{"state":"FL"}},{"guid":61,"values":{"state":"IL"}},{"guid":62,"values":{"state":"CA"}},{"guid":63,"values":{"state":"NY"}}],"caseName":null,"childAttrName":null,"collapseChildren":null,"guid":58,"name":"states","title":null,"type":"DG.Collection"},{"areParentChildLinksConfigured":false,"attrs":[{"name":"city","type":null,"title":"city","description":"","colormap":{"Minneapolis":{"h":0.6666666666666666,"s":0.6666666666666666,"b":1,"colorString":"rgb(85,85,255)"},"Miami":{"h":0.7555555555555555,"s":0.6666666666666666,"b":1,"colorString":"rgb(176,85,255)"},"Tampa":{"h":0.8444444444444444,"s":0.6666666666666666,"b":1,"colorString":"rgb(255,85,244)"},"Jacksonville":{"h":0.9333333333333333,"s":0.6666666666666666,"b":1,"colorString":"rgb(255,85,153)"},"St. Paul":{"h":0.022222222222222143,"s":0.6666666666666666,"b":1,"colorString":"rgb(255,108,85)"},"Orlando":{"h":0.11111111111111116,"s":0.6666666666666666,"b":1,"colorString":"rgb(255,198,85)"},"Chicago":{"h":0.20000000000000018,"s":0.6666666666666666,"b":1,"colorString":"rgb(221,255,85)"},"San Francisco":{"h":0.28888888888888875,"s":0.6666666666666666,"b":1,"colorString":"rgb(130,255,85)"},"New York":{"h":0.37777777777777777,"s":0.6666666666666666,"b":1,"colorString":"rgb(85,255,130)"}},"blockDisplayOfEmptyCategories":true,"editable":false,"guid":8,"precision":2,"unit":null}],"cases":[{"parent":59,"guid":49,"values":{"city":"Minneapolis"}},{"parent":59,"guid":53,"values":{"city":"St. Paul"}},{"parent":60,"guid":50,"values":{"city":"Miami"}},{"parent":60,"guid":51,"values":{"city":"Tampa"}},{"parent":60,"guid":52,"values":{"city":"Jacksonville"}},{"parent":60,"guid":54,"values":{"city":"Orlando"}},{"parent":61,"guid":55,"values":{"city":"Chicago"}},{"parent":62,"guid":56,"values":{"city":"San Francisco"}},{"parent":63,"guid":57,"values":{"city":"New York"}}],"caseName":null,"childAttrName":null,"collapseChildren":null,"guid":48,"name":"Cities","parent":58,"title":null,"type":"DG.Collection"},{"areParentChildLinksConfigured":false,"attrs":[{"name":"height","type":null,"title":"height","description":"","colormap":{},"blockDisplayOfEmptyCategories":true,"editable":false,"guid":4,"precision":2,"unit":"feet"},{"name":"stories","type":null,"title":"stories","description":"","colormap":{},"blockDisplayOfEmptyCategories":true,"editable":false,"guid":5,"precision":2,"unit":"stories"},{"name":"year_built","type":null,"title":"year_built","description":"","colormap":{},"blockDisplayOfEmptyCategories":true,"editable":false,"guid":7,"precision":2,"unit":null},{"name":"bldgID","type":null,"title":"bldgID","description":"","colormap":{},"blockDisplayOfEmptyCategories":true,"editable":false,"guid":6,"precision":2,"unit":null},{"name":"latitude","type":null,"title":"latitude","description":"","colormap":{},"blockDisplayOfEmptyCategories":true,"editable":false,"guid":10,"precision":2,"unit":null},{"name":"longitude","type":null,"title":"longitude","description":"","colormap":{},"blockDisplayOfEmptyCategories":true,"editable":false,"guid":11,"precision":2,"unit":null}],"cases":[{"parent":49,"guid":12,"values":{"height":787,"stories":51,"year_built":1973,"bldgID":"IDS Center","latitude":44.976074,"longitude":"-93.271884"}},{"parent":49,"guid":13,"values":{"height":777,"stories":57,"year_built":1988,"bldgID":"Norwest","latitude":44.953703,"longitude":"-93.239307"}},{"parent":49,"guid":14,"values":{"height":774,"stories":53,"year_built":1992,"bldgID":"First Bank Place","latitude":44.953703,"longitude":"-93.239307"}},{"parent":49,"guid":16,"values":{"height":627,"stories":42,"year_built":1984,"bldgID":"Piper Jaffray Tower","latitude":44.973653,"longitude":"-93.269872"}},{"parent":49,"guid":18,"values":{"height":545,"stories":40,"year_built":1981,"bldgID":"US Bank Plaza","latitude":44.973653,"longitude":"-93.239307"}},{"parent":49,"guid":22,"values":{"height":496,"stories":31,"year_built":1987,"bldgID":"Lincoln Centre","latitude":44.953703,"longitude":"-93.239307"}},{"parent":49,"guid":23,"values":{"height":494,"stories":36,"year_built":1987,"bldgID":"Plaza VII","latitude":44.953703,"longitude":"-93.239307"}},{"parent":49,"guid":24,"values":{"height":490,"stories":36,"year_built":1987,"bldgID":"100 South Fifth","latitude":44.953703,"longitude":"-93.239307"}},{"parent":49,"guid":33,"values":{"height":423,"stories":27,"year_built":1931,"bldgID":"Telephone Bldg","latitude":44.975833,"longitude":"-93.239307"}},{"parent":49,"guid":34,"values":{"height":413,"stories":24,"year_built":1974,"bldgID":"Hennepin Co. Govt. Center","latitude":44.975833,"longitude":"-93.239307"}},{"parent":49,"guid":36,"values":{"height":386,"stories":26,"year_built":1960,"bldgID":"First Bank Place West","latitude":44.953703,"longitude":"-93.239307"}},{"parent":49,"guid":37,"values":{"height":379,"stories":31,"year_built":1983,"bldgID":"Marriott Hotel","latitude":44.977504,"longitude":"-93.239307"}},{"parent":53,"guid":21,"values":{"height":517,"stories":32,"year_built":1931,"bldgID":"First Natl. Bank Bldg","latitude":44.953703,"longitude":"-93.239307"}},{"parent":53,"guid":26,"values":{"height":471,"stories":36,"year_built":1987,"bldgID":"Wells Fargo Place","latitude":44.953703,"longitude":"-93.239307"}},{"parent":53,"guid":32,"values":{"height":440,"stories":46,"year_built":"","bldgID":"Galtier Plaza's Jackson Tower","latitude":44.953703,"longitude":"-93.111034"}},{"parent":50,"guid":15,"values":{"height":764,"stories":55,"year_built":1983,"bldgID":"Southeast Financial Center","latitude":25.772198,"longitude":"-80.188148"}},{"parent":50,"guid":25,"values":{"height":484,"stories":35,"year_built":1986,"bldgID":"Florida National Tower","latitude":30.509418,"longitude":"-87.265003"}},{"parent":50,"guid":28,"values":{"height":456,"stories":40,"year_built":"","bldgID":"One Biscayne Corp","latitude":25.773902,"longitude":"-80.187885"}},{"parent":50,"guid":39,"values":{"height":375,"stories":32,"year_built":1973,"bldgID":"Amerifirst Bldg","latitude":25.76168,"longitude":"-80.191790"}},{"parent":51,"guid":17,"values":{"height":577,"stories":42,"year_built":1986,"bldgID":"Barnett Plaza","latitude":28.014218,"longitude":"-82.416346"}},{"parent":51,"guid":19,"values":{"height":537,"stories":39,"year_built":1981,"bldgID":"Tampa City Center","latitude":28.014218,"longitude":"-82.416346"}},{"parent":51,"guid":27,"values":{"height":458,"stories":36,"year_built":1973,"bldgID":"First Financial Tower","latitude":28.014218,"longitude":"-82.416346"}},{"parent":51,"guid":29,"values":{"height":454,"stories":33,"year_built":1988,"bldgID":"NCNB Plaza","latitude":28.014218,"longitude":"-82.416346"}},{"parent":52,"guid":20,"values":{"height":535,"stories":37,"year_built":1975,"bldgID":"Independent Square","latitude":30.332184,"longitude":"-81.655651"}},{"parent":52,"guid":30,"values":{"height":447,"stories":30,"year_built":1983,"bldgID":"Southern Bell","latitude":30.332184,"longitude":"-81.655651"}},{"parent":52,"guid":38,"values":{"height":375,"stories":23,"year_built":1989,"bldgID":"American Heritage Life","latitude":30.332184,"longitude":"-81.655651"}},{"parent":54,"guid":31,"values":{"height":441,"stories":31,"year_built":1988,"bldgID":"Sun Bank Center Tower","latitude":28.538335,"longitude":"-81.379236"}},{"parent":54,"guid":35,"values":{"height":409,"stories":28,"year_built":1988,"bldgID":"DuPont Center Bldg","latitude":28.538335,"longitude":"-81.379236"}},{"parent":55,"guid":40,"values":{"height":1450,"stories":108,"year_built":1973,"bldgID":"Willis Tower","latitude":41.878886,"longitude":"-87.635882"}},{"parent":56,"guid":41,"values":{"height":853,"stories":48,"year_built":1972,"bldgID":"Transamerica Pyramid","latitude":37.795162,"longitude":"-122.402728"}},{"parent":57,"guid":42,"values":{"height":1224,"stories":103,"year_built":1931,"bldgID":"Empire State Building","latitude":40.748441,"longitude":"-73.985664"}}],"caseName":null,"childAttrName":null,"collapseChildren":null,"guid":3,"name":"Buildings","parent":48,"title":null,"type":"DG.Collection"}],"contextStorage":{}}],"globalValues":[],"appName":"DG","appVersion":"2.0","appBuildNum":"0347","metadata":{"changeCount":2}}